Workbook

Sheet 环化大会26间酒店名单
A1: 环化大会26间酒店名单(截止11月22日20:00)
A2: 序号 | B2: 酒店名称 | C2: 酒店总房间数/间 | D2: 协议房间数/间 | E2: 已定房间数 | F2: 剩余房间数 | H2: 人数估计
A3: 1 | B3: 江门保利皇冠假日酒店 | C3: 290 | D3: 190 | E3: =贵宾酒店!J5+贵宾酒店!I25+贵宾酒店!J25 -> 159 | F3: 47 | H3: 280
A4: 2 | B4: 江门名冠金凯悦酒店 | C4: 516 | D4: 304 | E4: =贵宾酒店!I44+贵宾酒店!J44+贵宾酒店!J8 -> 248 | F4: =D4-E4 -> 56 | H4: 321
A5: 3 | B5: 江门富力万达嘉华酒店 | C5: 326 | D5: 252 | E5: =贵宾酒店!J6+贵宾酒店!J7+贵宾酒店!I34+贵宾酒店!J34 -> 215 | F5: =D5-E5 -> 37 | H5: 290
A6: 4 | B6: 江门丽宫国际酒店 | C6: 335 | D6: 288 | E6: 280 | F6: 8 | G6: 售罄 | H6: 392
A7: 5 | B7: 江门新会龙泉度假酒店 | C7: 380 | D7: 203 | E7: =贵宾酒店!I58+贵宾酒店!J58 -> 55 | F7: 165 | H7: 228
A8: 6 | B8: 江门新会碧桂园凤凰酒店 | C8: 374 | D8: 202 | E8: =贵宾酒店!I62+贵宾酒店!J62 -> 42 | F8: =D8-E8 -> 160 | H8: 55
A9: 7 | B9: 江门华保体育会展酒店（广东珠西国际会展中心店） | C9: 284 | D9: 100 | E9: =第一批上线!N4+第一批上线!O4 -> 55 | F9: =D9-E9 -> 45 | H9: 102
A10: 8 | B10: 江门银晶国际酒店 | C10: 218 | D10: 184 | E10: =第一批上线!I5+第一批上线!J5+第一批上线!N5+第一批上线!O5 -> 184 | F10: =D10-E10 -> 0 | G10: 售罄 | H10: 187
A11: 9 | B11: 江门蓬江华茵广场亚朵酒店 | C11: 90 | D11: 60 | E11: =第一批上线!I6+第一批上线!I7+第一批上线!N6+第一批上线!N7 -> 60 | F11: =D11-E11 -> 0 | G11: 售罄 | H11: 78
A12: 10 | B12: 铂顿国际公寓江门蓬江行政服务中心店 | C12: 87 | D12: 36 | E12: =第一批上线!I8+第一批上线!N8+第一批上线!N9 -> 36 | F12: =D12-E12 -> 0 | G12: 售罄 | H12: 52
A13: 11 | B13: 维也纳酒店(江门万达广场店) | C13: 60 | D13: 60 | E13: =第一批上线!I10+第一批上线!N10 -> 60 | F13: =D13-E13 -> 0 | G13: 售罄 | H13: 80
A14: 12 | B14: 维也纳酒店(江门常安路步行街店) | C14: 60 | D14: 50 | E14: =第一批上线!I11+第一批上线!N11 -> 49 | F14: =D14-E14 -> 1 | G14: 售罄 | H14: 68
A15: 13 | B15: 江海碧桂园凤凰酒店（江门东站万达广场店） | C15: 193 | D15: 125 | E15: 125 | F15: =D15-E15 -> 0 | G15: 售罄 | H15: 166
A16: 14 | B16: 江门江海智选假日酒店(江海广场店) | C16: 131 | D16: 47 | E16: =第一批上线!I13+第一批上线!N13 -> 47 | F16: =D16-E16 -> 0 | G16: 售罄 | H16: 62
A17: 15 | B17: 江门东站嘉华广场智选假日酒店 | C17: 128 | D17: 75 | E17: =第一批上线!I14+第一批上线!N14 -> 75 | F17: =D17-E17 -> 0 | G17: 售罄 | H17: 65
A18: 16 | B18: 全季酒店（江门东站江海万达广场店） | C18: 113 | D18: 62 | E18: =第一批上线!I15+第一批上线!N15+第一批上线!I16 -> 62 | F18: =D18-E18 -> 0 | G18: 售罄 | H18: 92
A19: 17 | B19: 绿岛假日酒店（江门万达广场华侨广场店） | C19: 166 | D19: 110 | E19: =第二批上线!I5+第二批上线!J5+第二批上线!N5+第二批上线!O5 -> 99 | F19: =D19-E19 -> 11 | G19: 售罄 | H19: 156
A20: 18 | B20: 江门合意酒店 | C20: 88 | D20: 25 | E20: =第二批上线!I6+第二批上线!J6+第二批上线!N6+第二批上线!O6 -> 19 | F20: =D20-E20 -> 6 | G20: 售罄 | H20: 30
A21: 19 | B21: 江门珺璟麦客达温德姆酒店 | C21: 80 | D21: 30 | E21: =第二批上线!I7+第二批上线!N7 -> 30 | F21: =D21-E21 -> 0 | G21: 售罄 | H21: 35
A22: 20 | B22: 希岸Deluxe酒店(江门外海大桥店) | C22: 151 | D22: 100 | E22: =第二批上线!I8+第二批上线!J8+第二批上线!N8+第二批上线!O8 -> 100 | F22: =D22-E22 -> 0 | G22: 售罄 | H22: 150
A23: 21 | B23: 江门奥普斯酒店（江门东站店） | C23: 116 | D23: 70 | E23: =第二批上线!I9+第二批上线!J9+第二批上线!N9+第二批上线!O9 -> 61 | F23: =D23-E23 -> 9 | G23: 售罄 | H23: 97
A24: 22 | B24: 柏丽泉智酒店（江门东站江海广场店） | C24: 70 | D24: 70 | E24: =第二批上线!N14+第二批上线!I14 -> 43 | F24: =D24-E24 -> 27 | H24: 59
A25: 23 | B25: 江门三木里酒店（江海站白水带公园店） | C25: 69 | D25: 46 | E25: =第二批上线!I10+第二批上线!N10+第二批上线!O10 -> 12 | F25: =D25-E25 -> 34 | H25: 16
A26: 24 | B26: 曼陀伦Plus智能酒店(江门和兴广场五邑华侨广场店) | C26: 61 | D26: 38 | E26: =第二批上线!I11+第二批上线!J11+第二批上线!N11+第二批上线!O11 -> 38 | F26: =D26-E26 -> 0 | G26: 售罄 | H26: 38
A27: 25 | B27: 曼陀伦智能酒店(江门职业技术学院店) | C27: 82 | D27: 54 | E27: =第二批上线!I12+第二批上线!J12+第二批上线!N12+第二批上线!O12 -> 23 | F27: =D27-E27 -> 31 | H27: 29
A28: 26 | B28: 丽枫酒店（迎宾大道店） | C28: 136 | D28: 120 | E28: 120 | F28: =D28-E28 -> 0 | G28: 售罄 | H28: 120
A29: 27 | B29: 古镇利和威斯汀酒店 | D29: 40 | E29: 0 | F29: =D29-E29 -> 40 | H29: 0
A30: 28 | B30: 古镇利和希尔顿花园 | D30: 40 | E30: 1 | F30: =D30-E30 -> 39 | H30: 0
A31: 29 | B31: 圭峰大酒店 | D31: 40 | E31: 1 | F31: =D31-E31 -> 39 | H31: 0
A32: 30 | B32: 凯里亚德酒店 | D32: 45 | E32: 1 | F32: =D32-E32 -> 44 | H32: 0
B33: 总计 | D33: =SUM(D3:D28) -> 2901 | E33: =SUM(E3:E28) -> 2297 | F33: =SUM(F3:F28) -> 637 | H33: =SUM(H3:H32) -> 3248

Sheet 贵宾酒店
A4: 序号 | B4: 贵宾类别 | C4: 酒店名称 | D4: 房型 | F4: 数量（间） | I4: 已售((截止11月4日23:59) | J4: 预留(截止11月17日17:00) | K4: 房价（元） | L4: 备注
A5: 1 | B5: VVIP | C5: 江门保利皇冠假日酒店（园山湖店） | D5: 皇冠套房 | F5: 5 | I5: 0 | J5: 0 | K5: 900 | L5: 不上线，VVIP专属套房
A6: 2 | C6: 江门富力万达嘉华酒店 | D6: 豪华套房 | F6: 10 | I6: 0 | J6: 10 | K6: 920
D7: 行政套房 | F7: 2 | I7: 0 | J7: 2 | K7: 920
A8: 3 | C8: 名冠金凯悦酒店 | D8: 豪华套房 | F8: 12 | I8: 0 | J8: 12 | K8: 519
D9: 豪华亲子套房 | F9: 9 | I9: 0 | J9: 9 | K9: 519
D10: 商务套房 | F10: 4 | I10: 0 | J10: 4 | K10: 920
D11: 行政套房 | F11: 5 | I11: 0 | J11: 5 | K11: 920
A12: 4 | C12: 江门丽宫国际酒店 | D12: A座套房 | F12: 8 | K12: 680
C13: 总合计 | F13: =SUM(F5:F12) -> 55 | I13: =SUM(I5:I12) -> 0 | J13: =SUM(J5:J12) -> 42
R14: 线上剩余房间数
F15: 全部总房间数 | G15: 现在线上总房间数 （不含预留不上线房间数） | H15: 减去预留房间数 | I15: 线上已售房间数 | J15: 预留房间数 | T15: 组委免住宿预留表格 | U15: 团房扫码预留表格 | V15: 外籍专家预留表格
I16: 已售（截止11月21日18:00） | J16: (截止11月19日20：00)
A17: 1 | B17: VIP | C17: 江门保利皇冠假日酒店（园山湖店） | D17: 高级大床房（单早） | F17: 20 | G17: 20 | I17: 16 | K17: 450 | L17: 10月8日上线 105间 | M17: =F17-I17-J17 -> 4 | R17: =G17-I17 -> 4
D18: 高级双床房（双早） | F18: 35 | G18: 27 | I18: 27 | J18: 8 | K18: 510 | M18: =F18-I18-J18 -> 0 | R18: =G18-I18 -> 0
D19: 高级城景大床房（单早） | F19: 20 | G19: 12 | H19: =20-J19 -> 12 | I19: 12 | J19: 8 | K19: 500 | M19: =F19-I19-J19 -> 0 | N19: 郑焰房间在预留1间房间数中 | R19: =G19-I19 -> 0 | T19: 9
D20: 高级湖景双床房（双早） | F20: 30 | G20: 30 | H20: =30-J20 -> 30 | I20: 30 | K20: 610 | M20: =F20-I20-J20 -> 0 | R20: =G20-I20 -> 0
D21: 行政双床房 | F21: 10 | G21: 10 | H21: =10-J21 -> 10 | I21: 5 | K21: 758 | M21: =F21-I21-J21 -> 5 | R21: =G21-I21 -> 5
D22: 高级城景双床房（双早） | F22: 20 | G22: 20 | H22: =20-J22 -> 18 | I22: 12 | J22: 2 | K22: 560 | M22: =F22-I22-J22 -> 6 | R22: =G22-I22 -> 8
D23: 行政大床房 | F23: 20 | G23: 12 | H23: =20-J23 -> 17 | I23: 9 | J23: 3 | K23: 758 | M23: =F23-I23-J23 -> 8
D24: 高级湖景大床房（单早） | F24: 30 | G24: 26 | H24: =30-J24 -> 26 | I24: 23 | J24: 4 | K24: 550 | M24: =F24-I24-J24 -> 3 | T24: 3
D25: 合计 | F25: =SUM(F17:F24) -> 185 | I25: =SUM(I17:I24) -> 134 | J25: =SUM(J17:J24) -> 25 | M25: =SUM(M17:M24) -> 26
F26: =F17+F19+F23+F24 -> 90 | G26: =F25-F26 -> 95 | H26: =F26+G26*2 -> 280
A27: 2 | C27: 江门富力万达嘉华酒店 | D27: 豪华大床房（单早） | E27: 60 | F27: 60 | G27: 49 | I27: 48 | J27: 12 | K27: 470 | L27: 10月8日上线 138间 | M27: =F27-I27-J27 -> 0 | N27: 42+8（线下预留）=50 | Q27: 已扣减平台预定赵美训、万莹、张山青5间房间 | R27: =G27-I27 -> 1 | T27: 7 | V27: 4
D28: 豪华双床房（双早） | E28: 43 | F28: 43 | G28: 43 | I28: 41 | J28: 2 | K28: 470 | M28: =F28-I28-J28 -> 0 | N28: 49+1（线下预留）=50 | R28: =G28-I28 -> 2
D29: 高级双床房（双早） | E29: 20 | F29: 20 | G29: 19+1 | I29: 19 | J29: 0 | K29: 470 | M29: =F29-I29-J29 -> 1 | R29: =G29-I29 -> #VALUE!
D30: 行政大床房（单早） | E30: 33 | F30: 28 | G30: 28 | I30: 27 | K30: 470 | M30: =F30-I30-J30 -> 1 | R30: =G30-I30 -> 1
D31: 行政大床房（单早） | E31: 12 | F31: 17 | G31: 17 | H31: =17-J31 -> 2 | I31: 0 | J31: 15 | K31: 470 | L31: 预留72间 | M31: =F31-I31-J31 -> 2 | R31: =F32-I32 -> 12 | T31: 1
D32: 行政双床房（双早） | E32: 12 | F32: 12 | G32: 3 | H32: =12-J32 -> 1 | I32: 0 | J32: 11 | K32: 470 | M32: =F32-I32-J32 -> 1 | R32: =F33-J33 -> 32 | T32: 9
D33: 高级大床房（单早） | E33: 60 | F33: 60 | G33: 31 | H33: =60-J33 -> 32 | I33: 0 | J33: 28 | K33: 470 | M33: =F33-I33-J33 -> 32 | N33: 23（线下预留），为避免后续此房型上线预订时出现超房情况，线上改为27间，总房数23+27=50 | T33: 29
D34: 合计 | F34: =SUM(F27:F33) -> 240 | I34: =SUM(I27:I33) -> 135 | J34: =SUM(J27:J33) -> 68 | M34: =SUM(M27:M33) -> 37
F35: =F27+F30+F31+F33 -> 165 | G35: =F34-F35 -> 75 | H35: =F35+G35*2 -> 315
A36: 3 | C36: 名冠金凯悦酒店 | D36: 高级大床房（单早） | F36: 21 | G36: 21 | I36: 21 | K36: 399 | M36: 0 | R36: =G36-I36 -> 0
D37: 高级双床房（双早） | F37: 42 | G37: 42 | I37: 42 | K37: 399 | M37: 0 | R37: =G37-I37 -> 0
D38: 豪华大床房（单早） | F38: 54 | G38: 44 | H38: =54-J38 -> 25 | I38: 25 | J38: 29 | K38: 438 | L38: 10月8日上线 134间 | M38: =F38-I38-J38 -> 0 | N38: 54-3（线下预留）=51（系统显示总房数） | R38: =G38-I38 -> 19 | T38: 9 | V38: 1
D39: 豪华双床房（双早） | F39: 30 | G39: 26 | I39: 16 | J39: 13 | K39: 438 | M39: =F39-I39-J39 -> 1 | R39: =G39-I39 -> 10
D40: 主题养生单人房（单早） | F40: 44 | G40: 40 | H40: =44-J40 -> 12 | I40: 9 | J40: 32 | K40: 470 | M40: =F40-I40-J40 -> 3 | N40: 44-1（线下预留）=43（系统显示总房数） | R40: =G40-I40 -> 31 | T40: 3 | U40: 1
D41: 臻享商务单人房（单早） | F41: 15 | G41: 13 | H41: =15-J41 -> 9 | I41: 9 | J41: 6 | K41: 470 | M41: =F41-I41-J41 -> 0 | N41: 15-2（线下预留）=13（系统显示总房数） | R41: =G41-I41 -> 4 | T41: 4
D42: 行政单人房（单早） | F42: 17 | G42: 17 | H42: =17-J42 -> 16 | I42: 0 | J42: 1 | K42: 550 | M42: =G42-I42-J42 -> 16
D43: 商务单人房（单早） | F43: 51 | G43: 51 | H43: =51-J43 -> 18 | I43: 0 | J43: 33 | K43: 470 | M43: =G43-I43-J43 -> 18 | T43: 1
D44: 合计 | F44: =SUM(F36:F43) -> 274 | I44: =SUM(I36:I43) -> 122 | J44: =SUM(J36:J43) -> 114 | M44: =SUM(M36:M43) -> 38
F45: =F36+F38+F40+F41+F42+F43 -> 202 | G45: =F44-F45 -> 72 | H45: =F45+G45*2 -> 346
A46: 4 | C46: 江门丽宫国际酒店 | D46: A座高级大床房（单早） | F46: 16 | G46: 16 | I46: 15 | K46: 300 | L46: 10月8日上线 57间 | M46: =F46-I46-J46 -> 1 | R46: =G46-I46 -> 1
D47: A座高级双床房（双早） | F47: 24 | G47: 24 | I47: 23 | K47: 300 | M47: =F47-I47-J47 -> 1 | R47: =G47-I47 -> 1
D48: A座智能大床房（单早） | F48: 35 | G48: 27 | I48: 26 | J48: 8 | K48: 320 | M48: =F48-I48-J48 -> 1 | R48: =G48-I48 -> 1
D49: A座豪华双床房（单早） | F49: 45 | G49: 45 | I49: 44 | K49: 320 | M49: =F49-I49-J49 -> 1 | R49: =G49-I49 -> 1
D50: 至尊大床房（单早） | F50: 7 | G50: 7 | I50: 7 | K50: 320 | M50: =F50-I50-J50 -> 0 | R50: =G50-I50 -> 0
D51: 至尊双床房（双早） | F51: 9 | G51: 9 | I51: 9 | K51: 320 | M51: =F51-I51-J51 -> 0 | R51: =G51-I51 -> 0
D52: 合计 | F52: =SUM(F46:F51) -> 136 | G52: 128 | H52: =F52+G52*2 -> 392 | I52: =SUM(I46:I51) -> 124 | J52: 8 | M52: =SUM(M46:M51) -> 4
F53: =F46+F48+F49+F50 -> 103 | G53: =F52-F53 -> 33
A54: 5 | C54: 江门新会龙泉度假酒店（有温矿泉） | D54: 豪华大床房（单早） | F54: 28 | G54: 28 | I54: 27 | J54: 1 | K54: 540 | L54: 10月8日上线 153间 | M54: =F54-I54-J54 -> 0 | R54: =G54-I54 -> 1
D55: 豪华双床房（双早） | F55: 60 | G55: 60 | I55: 28 | K55: 450 | M55: =F55-I55-J55 -> 32 | R55: =G55-I55 -> 32
D56: 豪华大床房（单早） | F56: 20 | G56: 0 | H56: =20-J56 -> 0 | I56: 0 | J56: 20 | K56: 540 | L56: 预留50间 | M56: =F56-I56-J56 -> 0 | R56: =G56-I56 -> 0 | T56: 4
D57: 豪华双床房（双早） | F57: 30 | G57: 0 | H57: =F57-J57 -> 24 | I57: 0 | J57: 6 | K57: 450 | M57: =F57-I57-J57 -> 24 | R57: 30 | T57: 1
D58: 合计 | F58: =SUM(F54:F57) -> 138 | I58: =SUM(I54:I57) -> 55 | M58: =SUM(M54:M57) -> 56
F59: =F54+F56 -> 48 | G59: =F58-F59 -> 90 | H59: =F59+G59*2 -> 228
A60: 6 | C60: 江门新会碧桂园凤凰酒店 | D60: 高级大床房（单早） | F60: 34 | G60: 6 | H60: =30-J60 -> 7 | I60: 11 | J60: =T60+U60+V60 -> 23 | K60: 280 | L60: 待定，预留 230间 | M60: =F60-I60-J60 -> 0 | T60: 23
D61: 高级双床房（双早） | F61: 168 | G61: 168 | H61: 168 | I61: 6 | J61: =T61+U61+V61 -> 2 | K61: 280 | M61: =F61-I61-J61 -> 160 | N61: 含司陪 | T61: 2
D62: 合计 | F62: 230 | I62: =SUM(I60:I61) -> 17 | J62: =SUM(J60:J61) -> 25 | M62: =SUM(M60:M61) -> 160
F63: =F60 -> 34 | G63: =F61 -> 168 | H63: =F63+G63*2 -> 370
D64: 总计 | F64: =F25+F34+F44+F58+F62+F52 -> 1203 | I64: =I58+I52+I44+I34+I25+I13 -> 570 | J64: =J58+J52+J44+J34+J25+J13 -> 257 | M64: =F64-I64-J64 -> 376
D65: 第一批+10.8日上线合计 | F65: =SUM(F17:F22)+SUM(F27:F30)++SUM(F36:F41)+SUM(F46:F51)++SUM(F54:F55) -> 716 | I65: =I64+J64 -> 827
D66: 三大酒店+龙泉预留合计 | F66: =F64-F65-230 -> 257
D67: 待定，预留 | F67: 230间
C70: *因线下预留用房存在部分无法通过线上系统完成登记的情况，为防范各酒店发生超房风险，相关操作将为：针对系统不可登记的线下预留用房，在系统总房数内予以对应数量扣减。
B83: VIP酒店 | C83: 第一批+10.8日第二批上线 | D83: 截止10.26日15:30未订房间数量 | F83: 未上线但已被预留 | G83: 可上线房间数 | I83: 总数
B84: 保利 | C84: 125 | D84: 94 | F84: 2 | G84: 58 | I84: =C84+F84+G84 -> 185
B85: 金凯悦 | C85: 198 | D85: 71 | F85: 0 | G85: 75 | I85: =C85+F85+G85 -> 273
B86: 万达 | C86: 148 | D86: 3 | F86: 25 | G86: =72-F86 -> 47 | I86: =C86+F86+G86 -> 220
B87: 丽宫 | C87: 136 | D87: 3 | F87: 0 | G87: 0 | I87: 136
B88: 龙泉 | C88: 153 | D88: 152 | F88: 0 | G88: 50 | I88: =C88+G88 -> 203
B89: 总数 | C89: =SUM(C84:C88) -> 760 | D89: =SUM(D84:D88) -> 323 | F89: =SUM(F84:F88) -> 27 | G89: =SUM(G84:G88) -> 230 | I89: =SUM(I84:I88) -> 1017
B91: 普通酒店 | C91: 第一批上线+第二批上线 | D91: 截止10.26日16:30已订数量 | F91: 截止10.26日16:30未订房间数量
B92: 江门华保体育会展酒店（广东珠西国际会展中心滨江体育中心店） | C92: 200 | D92: 21 | F92: =C92-D92 -> 179
B93: 江门银晶国际酒店 | C93: =69+69+46 -> 184 | D93: =63+41+46 -> 150 | F93: =C93-D93 -> 34
B94: 江门蓬江华茵广场亚朵酒店 | C94: 60 | D94: 60 | F94: =C94-D94 -> 0
B95: 铂顿国际公寓江门蓬江行政服务中心店 | C95: 36 | D95: 36 | F95: =C95-D95 -> 0
B96: 维也纳酒店(江门万达广场店) | C96: 60 | D96: 60 | F96: =C96-D96 -> 0
B97: 维也纳酒店(江门常安路步行街店) | C97: 49 | D97: 35 | F97: =C97-D97 -> 14
B98: 江海碧桂园凤凰酒店（江门东站万达广场店） | C98: 184 | D98: 10 | F98: =C98-D98 -> 174
B99: 江门江海智选假日酒店(江海广场店) | C99: 60 | D99: 32 | F99: =C99-D99 -> 28
B100: 江门东站嘉华广场智选假日酒店 | C100: 121 | D100: 6 | F100: =C100-D100 -> 115
B101: 全季酒店（江门东站江海万达广场店） | C101: 63 | D101: 49 | F101: =C101-D101 -> 14
B102: 江门丽宫国际酒店B座 | C102: 144 | D102: 57 | F102: =C102-D102 -> 87
B103: 绿岛假日酒店（江门万达广场华侨广场店） | C103: 120 | D103: 0 | F103: =C103-D103 -> 120
B104: 江门合意酒店 | C104: 35 | D104: 0 | F104: =C104-D104 -> 35
B105: 江门珺璟麦客达温德姆酒店 | C105: 30 | D105: 14 | F105: =C105-D105 -> 16
... B114: 江门新会花季酒店 | C114: 35 | D114: 0 | F114: =C114-D114 -> 35
C115: 21 | D115: 0 | F115: =C115-D115 -> 21
B116: 江门新会希尔顿花园酒店 | C116: 45 | D116: 0 | F116: =C116-D116 -> 45
C117: 55 | D117: 0 | F117: =C117-D117 -> 55
B118: 新会圭峰大酒店 | C118: 100 | D118: 0 | F118: =C118-D118 -> 100
B119: 非繁城品酒店·新会步行街店 | C119: 60 | D119: 0 | F119: =C119-D119 -> 60
B120: 广东鹤山方圆福朋喜来登酒店 | C120: 190 | D120: 0 | F120: =C120-D120 -> 190
B121: 中山市古镇镇华艺广场亚朵酒店 | C121: 120 | D121: 0 | F121: =C121-D121 -> 120
B122: 维也纳国际酒店(中山古镇华艺广场店） | C122: 100 | D122: 0 | F122: =C122-D122 -> 100
B123: 利和希尔顿花园酒店 | C123: 40 | D123: 0 | F123: =C123-D123 -> 40
B124: 中山利和威斯汀酒店 | C124: 80 | D124: 0 | F124: =C124-D124 -> 80
B125: 总数 | C125: =SUM(C92:C124) -> 2816 | D125: =SUM(D92:D124) -> 543 | F125: =SUM(F92:F124) -> 2273

Sheet 第一批上线
A1: 环化大会第一批可上线酒店
A2: 片区 | B2: 序号 | C2: 酒店名称 | D2: 酒店给房数 | E2: 酒店类型 | F2: 大床房 | K2: 双床房
F3: 房型说明 | G3: 房价（元/晚） | H3: 数量（间） | I3: 已售（截止11月17日15:30） | J3: 预留(截止11月12日23:59) | K3: 房型说明 | L3: 房价（元/晚） | M3: 数量（间） | N3: 已售（截止11月17日15:30） | O3: 预留(截止11.19
B4: 1 | C4: 江门华保体育会展酒店（广东珠西国际会展中心滨江体育中心店） | D4: 60 | E4: 商务 | K4: 双床房（双早） | L4: —— | M4: 100 | N4: 55
B5: 2 | C5: 江门银晶国际酒店 | D5: =H5+M5 -> 184 | E5: 商务 | F5: 大床房（含双早） | G5: 200 | H5: 69 | I5: 69 | J5: 0 | K5: 双床房（含双早） | L5: —— | M5: 115 | N5: 69 | O5: 46 | P5: 售罄
B6: 3 | C6: 江门蓬江华茵广场亚朵酒店 | D6: =H6+H7+M6+M7 -> 60 | E6: 商务 | F6: 行政大床房（双早） | G6: 450 | H6: 20 | I6: 20 | K6: 行政双床房（双早） | L6: —— | M6: 10 | N6: 10 | P6: 售罄
F7: 几木大床房（双早） | G7: 500 | H7: 20 | I7: 20 | K7: 几木双床房（双早） | L7: 450 | M7: 10 | N7: 10 | P7: 售罄
B8: 4 | C8: 铂顿国际公寓江门蓬江行政服务中心店 | D8: =H8+H9+M8+M9 -> 36 | E8: 商务 | F8: 豪华城景大床-含早 | G8: 356 | H8: 20 | I8: 20 | K8: 豪华城景双床-含早 | L8: 500 | M8: 8 | N8: 8 | P8: 售罄
K9: 轻奢城景双床-含早 | L9: 311 | M9: 8 | N9: 8 | P9: 售罄
B10: 5 | C10: 维也纳酒店(江门万达广场店) | D10: =H10+M10 -> 60 | E10: 商务 | F10: 大床房-含早 | G10: 318 | H10: 40 | I10: 40 | K10: 双床房-含早 | L10: 359 | M10: 20 | N10: 20 | P10: 售罄
B11: 6 | C11: 维也纳酒店(江门常安路步行街店) | D11: =H11+M11 -> 50 | E11: 舒适型 | F11: 豪华大床-含早 | G11: 200 | H11: 30 | I11: 30 | K11: 豪华双床-含早 | L11: 338 | M11: 20 | N11: 19 | O11: 1 | P11: 售罄
A12: 江海区 | B12: 7 | C12: 江海碧桂园凤凰酒店（江门东站万达广场店） | D12: =H12+M12 -> 125 | E12: 商务 | F12: 大床房（单早） | G12: 260 | H12: 54 | I12: 44 | J12: 10 | K12: 双床房（双早） | L12: 200 | M12: 71 | N12: 61 | O12: 10 | P12: =H12-I12-J12-N12-O12+M12 -> 0 | Q12: 售罄
B13: 8 | C13: 江门江海智选假日酒店(江海广场店) | D13: =H13+M13 -> 47 | E13: 商务 | F13: 大床房（单早） | G13: 299 | H13: 32 | I13: 32 | K13: 双床房（双早） | L13: 260 | M13: 15 | N13: 15 | P13: 售罄
B14: 9 | C14: 江门东站嘉华广场智选假日酒店 | D14: =H14+M14 -> 75 | E14: 商务 | F14: 大床房（单早） | G14: 289 | H14: 40 | I14: 40 | K14: 双床房（双早） | L14: 299 | M14: 35 | N14: 35 | P14: 售罄
B15: 10 | C15: 全季酒店（江门东站江海万达广场店） | D15: =H15+M15+H16 -> 62 | E15: 商务 | F15: 大床房（单早） | G15: 300 | H15: 30 | I15: 30 | K15: 双床房（双早） | L15: 289 | M15: 30 | N15: 30 | P15: 售罄
F16: 套房（含早） | G16: 480 | H16: 2 | I16: 2 | K16: —— | L16: 300 | P16: 售罄
A17: 合计 | D17: =H17+M17 -> 799 | E17: - | H17: =SUM(H4:H16) -> 357 | I17: =SUM(I4:I16) -> 347 | J17: =SUM(J4:J16) -> 10 | L17: —— | M17: =SUM(M4:M16) -> 442 | N17: =SUM(N4:N15) -> 340 | O17: =SUM(O4:O16) -> 57
D20: 已订 | E20: =I17+N17+J17+O17 -> 754 | H20: 余房 | I20: =H17+M17-I17-J17-N17-O17 -> 45
D21: 余房 | E21: =D17-I17-N17-J17-O17 -> 45

Sheet 第二批上线
A1: 环化大会拟第二批上线酒店
A2: 序号 | B2: 酒店名称 | C2: 酒店总房数 | D2: 给房数 | E2: 酒店类型 | F2: 大床房 | K2: 双床房
F3: 房型说明 | G3: 房价（元/晚） | H3: 数量（间） | I3: 已售(截止11月14日15:30) | J3: 预留（截止11月17日15:30） | K3: 房型说明 | L3: 房价（元/晚） | M3: 数量（间） | N3: 已售（截止11月17日15:30） | O3: 预留(截止11月19日18:50)
A4: 1 | B4: 江门丽宫国际酒店B座 | C4: 335 | D4: =H4+M4 -> 144 | E4: 豪华 | F4: B座陈韵雅致大床（双早） | G4: 248 | H4: 96 | I4: 77 | J4: 12 | K4: B座陈韵雅致双床（双早） | L4: 248 | M4: 48 | N4: 48 | P4: =H4-I4-J4+M4-N4 -> 7 | Q4: 售罄
A5: 3 | B5: 绿岛假日酒店（江门万达广场华侨广场店） | C5: 166 | D5: =H5+M5 -> 119 | E5: 商务 | F5: ——（含双早） | G5: 200 | H5: 39 | I5: 34 | J5: 5 | K5: ——（含双早） | L5: 200 | M5: 80 | N5: 51 | O5: 9 | P5: 售罄
A6: 4 | B6: 江门合意酒店 | D6: =H6+M6 -> 35 | E6: 商务 | F6: ——（含双早） | G6: 238 | H6: 20 | I6: 15 | K6: ——（含双早） | L6: 238 | M6: 15 | N6: 4 | P6: 售罄
A7: 5 | B7: 江门珺璟麦客达温德姆酒店 | C7: 80 | D7: =H7+M7 -> 30 | E7: 准四 | F7: 大床房（单早） | G7: 300 | H7: 25 | I7: 25 | K7: 双床房（双早） | L7: 360 | M7: 5 | N7: 5 | P7: 售罄
A8: 6 | B8: 希岸Deluxe酒店(江门外海大桥店) | C8: 151 | D8: =H8+M8 -> 100 | E8: 商务 | F8: 江景大床房（单早） | G8: 360 | H8: 50 | I8: 50 | K8: 商务双床房（双早） | L8: 360 | M8: 50 | N8: 50 | P8: 售罄
A9: 7 | B9: 江门奥普斯酒店（江门东站店） | C9: 116 | D9: =H9+M9 -> 70 | E9: 商务 | F9: 大床房（单早） | G9: 240 | H9: 40 | I9: 37 | J9: 2 | K9: 双床房（双早） | L9: 260 | M9: 30 | N9: 22 | P9: 售罄
A10: 11 | B10: 江门三木里酒店（江海站白水带公园店） | C10: 69 | D10: =H10+M10 -> 46 | E10: 商务 | F10: 大床房（单早） | G10: 258 | H10: 28 | I10: 8 | K10: 双床房（双早） | L10: 280 | M10: 18 | N10: 4
A11: 12 | B11: 曼陀伦Plus智能酒店(江门和兴广场五邑华侨广场店) | C11: 61 | D11: =H11+M11 -> 38 | E11: 商务 | F11: 大床房（单早） | G11: 270 | H11: 33 | I11: 33 | K11: 双床房（双早） | L11: 280 | M11: 5 | N11: 5 | P11: 售罄
A12: 13 | B12: 曼陀伦智能酒店(江门职业技术学院店) | C12: 82 | D12: =H12+M12 -> 54 | E12: 商务 | F12: 大床房（单早） | G12: 200 | H12: 36 | I12: 15 | K12: 双床房（双早） | L12: 200 | M12: 18 | N12: 8
B13: 丽枫酒店（迎宾大道店） | D13: 120 | F13: 大床房（单早） | G13: 250 | H13: 70 | I13: 45 | J13: 24 | K13: 双床房（双早） | L13: 270 | M13: 50 | N13: 0 | O13: 50 | P13: 1
B14: 柏丽泉智酒店（江门东站江海广场店） | D14: 70 | F14: 大床房（单早） | G14: 258 | H14: 50 | I14: 25 | J14: 1 | K14: 双床房（双早） | L14: 258 | M14: 20 | N14: 18
E15: - | F15: =H15+M15 -> 826 | H15: =SUM(H4:H14) -> 487 | I15: =SUM(I4:I14) -> 364 | J15: =SUM(J4:J14) -> 44 | M15: =SUM(M4:M14) -> 339 | N15: =SUM(N4:N14) -> 215 | O15: =SUM(O4:O14) -> 59
G18: 余房 | H18: =F15-I15-J15-N15-O15 -> 144

Sheet 组委会预留名单
A1: 组委会预留名单
A2: 姓名 | B2: 院校 | C2: 入住酒店 | D2: 房型 | E2: 入住日期 | F2: 退房日期 | G2: 入住天数 | H2: 房间数量（间） | I2: 酒店单价（元） | J2: 应收房费（元） | K2: 备注 | L2: 信息来源
A3: 许继文 | B3: 南科大 资助81人,41间房 | C3: 江门银晶国际酒店 | D3: 双床房（含双早） | E3: 45989 | F3: 45991 | G3: =F3-E3 -> 2 | H3: 1 | I3: 200 | J3: =I3*H3*G3 -> 400
A4: 10人 | E4: 45989 | F4: 45992 | G4: 3 | H4: 5 | I4: 200 | J4: =G4*H4*I4 -> 3000
A5: 69人 | E5: 45989 | F5: 45993 | G5: 4 | H5: 35 | I5: 200 | J5: =G5*H5*I5 -> 28000 | K5: 免住宿 | L5: 刘长宇
A6: 江桂斌（院士） | B6: 中国科学院生态环境研究中心 | C6: 江门富力万达嘉华酒店 | D6: 行政套房 | E6: 45989 | F6: 45993 | G6: 4 | H6: 1 | I6: 920 | J6: 3680 | K6: 线下付款，不能催付款 | L6: 刘长宇
A7: 李景虹（院士） | B7: 清华大学 | C7: 江门富力万达嘉华酒店 | D7: 豪华套房 | E7: 45989 | F7: 45991 | G7: 2 | H7: 1 | I7: 920 | J7: 1840 | K7: 免住宿 | L7: 刘长宇
A8: 薛其坤（院士） | B8: 中国科学院院士 | C8: 江门富力万达嘉华酒店 | D8: 行政套房 | E8: 45989 | F8: 45991 | G8: 2 | H8: 1 | I8: 920 | J8: =G8*H8*I8 -> 1840 | K8: 免住宿，万达最好套房，近江院士房间 | L8: 刘长宇 | M8: 已与万达经理沟通，安排的两个行政套房在同一层，间隔10米
A9: Susan D. Richardson | B9: University of South Carolina | C9: 江门富力万达嘉华酒店 | D9: 豪华套房 | E9: 45990 | F9: 45993 | G9: 3 | H9: 1 | I9: 470 | J9: 1410 | K9: 免住宿 | L9: 刘长宇
A10: Fabio Pulizzi | C10: 江门富力万达嘉华酒店 | D10: 豪华套房 | E10: 45992 | F10: 45994 | G10: 2 | H10: 1 | I10: 920 | J10: =G10*H10*I10 -> 1840 | K10: 免住宿 | L10: 刘长宇29
A11: 万莹 | B11: 基金委 | C11: 江门富力万达嘉华酒店 | D11: 豪华大床房 | E11: 45989 | F11: 45992 | G11: =F11-E11 -> 3 | H11: 0 | I11: 470 | J11: 1880 | K11: 免住宿，预订平台已登记1间 | L11: 刘长宇
A12: 庄乾坤 | C12: 江门富力万达嘉华酒店 | D12: 豪华大床房 | E12: 45991 | G12: 4 | H12: 1 | I12: 470 | J12: 1880 | K12: 免住宿 | L12: 刘长宇
A13: 王春霞 | C13: 江门富力万达嘉华酒店 | D13: 豪华大床房 | E13: 待定 | G13: 4 | H13: 1 | I13: 470 | J13: 1880 | K13: 免住宿 | L13: 刘长宇
A14: 余立风 | C14: 江门富力万达嘉华酒店 | D14: 豪华大床房 | E14: 待定 | H14: 1 | I14: 470 | K14: 免住宿
A17: 张金龙（院士） | B17: 华东理工大学 | C17: 名冠金凯悦酒店 | D17: 豪华套房 | E17: 45989 | F17: 45992 | G17: 3 | H17: 1 | I17: 519 | J17: =G17*H17*I17 -> 1557 | K17: 免住宿 | L17: 刘长宇
A18: 朱利中（院士） | B18: 浙江大学 | C18: 江门富力万达嘉华酒店 | D18: 豪华套房 | E18: 45989 | F18: 45992 | G18: 3 | H18: 1 | I18: 920 | J18: 2760 | K18: 免住宿，预订平台已登记
A19: 陈春城 | B19: 中国科学院化学研究所 | C19: 名冠金凯悦酒店 | D19: 商务单人房 | E19: 45989 | F19: 45992 | G19: =F19-E19 -> 3 | H19: 1 | I19: 470 | J19: =G19*H19*I19 -> 1410 | K19: 专家自付
A20: 张涛院士 | B20: 张涛院士 | C20: 江门富力万达嘉华酒店 | D20: 豪华套房 | E20: 45989 | H20: 1 | I20: 920 | K20: 大会免住宿 | L20: 2张餐票，最好的套房 （带家属）
B21: 院士随行人员 | C21: 江门富力万达嘉华酒店 | D21: 高级大床房 | E21: 45989 | H21: 1 | I21: 470
A22: 刘维屏 | B22: 专委会委员 | C22: 江门富力万达嘉华酒店 | D22: 高级大床房 | E22: 45989 | F22: 45992 | G22: =F22-E22 -> 3 | H22: 1 | I22: 470 | J22: =G22*H22*I22 -> 1410 | K22: 专家自付
A23: 阚海东 | C23: 江门富力万达嘉华酒店 | D23: 高级大床房 | E23: 45989 | F23: 45991 | G23: =F23-E23 -> 2 | H23: 1 | I23: 470 | J23: =G23*H23*I23 -> 940
A24: 要茂盛 | C24: 江门富力万达嘉华酒店 | D24: 高级大床房 | E24: 45988 | H24: 1 | I24: 470
A25: 冯新斌 | C25: 江门富力万达嘉华酒店 | D25: 高级大床房 | E25: 45989 | F25: 45992 | G25: =F25-E25 -> 3 | H25: 1 | I25: 470 | J25: =G25*H25*I25 -> 1410
A26: 王秋泉 | C26: 江门富力万达嘉华酒店 | D26: 高级大床房 | E26: 45988 | F26: 45991 | G26: =F26-E26 -> 3 | H26: 1 | I26: 470 | J26: =G26*H26*I26 -> 1410
A27: 吴永宁 | C27: 江门富力万达嘉华酒店 | D27: 高级大床房 | E27: 45989 | F27: 45992 | G27: =F27-E27 -> 3 | H27: 1 | I27: 470 | J27: =G27*H27*I27 -> 1410
A28: 孙红文 | C28: 江门富力万达嘉华酒店 | D28: 高级大床房 | E28: 45989 | F28: 45992 | G28: =F28-E28 -> 3 | H28: 1 | I28: 470 | J28: =G28*H28*I28 -> 1410
A29: 吴永宁 | C29: 江门富力万达嘉华酒店 | D29: 高级大床房 | E29: 45989 | F29: 45991 | G29: =F29-E29 -> 2 | H29: 1 | I29: 470 | J29: =G29*H29*I29 -> 940
A30: 宋茂勇 | C30: 江门富力万达嘉华酒店 | D30: 高级大床房 | E30: 45989 | F30: 45992 | G30: =F30-E30 -> 3 | H30: 1 | I30: 470 | J30: =G30*H30*I30 -> 1410
H31: =SUM(H3:H28) -> 61
A32: 俞汉青（院士） | B32: 中国科学技术大学 | C32: 江门富力万达嘉华酒店 | D32: 行政大床房 | E32: 45989 | F32: 45993 | G32: 4 | H32: 1 | I32: 470 | J32: 1880 | K32: 免住宿 | L32: 刘长宇
A33: 陶澍 | B33: 北京大学 | C33: 名冠金凯悦酒店 | D33: 行政套房 | H33: 1
A34: 付贤智 | B34: 福州大学 | C34: 名冠金凯悦酒店 | D34: 行政套房 | E34: 45989 | F34: 45990 | G34: =F34-E34 -> 1 | H34: 1 | I34: 920 | J34: =I34*H34*G34 -> 920
B35: 付贤智院士陪同人员 | C35: 名冠金凯悦酒店 | D35: 商务单人房 | E35: 45989 | F35: 45990 | G35: =F35-E35 -> 1 | H35: 1 | I35: 470 | J35: =I35*H35*G35 -> 470
A36: 柴之芳（夫妇） | B36: 中国科学院高能物理研究所 | C36: 名冠金凯悦酒店 | D36: 行政套房 | H36: 1 | L36: 两张餐票，要最好的套房（带家属）
A37: 沈洪兵 | B37: 国家卫生健康委员会 | C37: 江门富力万达嘉华酒店 | D37: 豪华套房 | E37: 45990 | F37: 45991 | H37: 1 | I37: 920 | L37: 要最好的套房
A38: 郝吉明 | B38: 清华大学 | C38: 名冠金凯悦酒店 | D38: 行政套房 | H38: 1
A39: 汪华林 | B39: 华东理工大学 | C39: 名冠金凯悦酒店 | D39: 商务套房 | H39: 1
A40: 杨志峰 | B40: 广东工业大学 | C40: 名冠金凯悦酒店 | D40: 商务套房 | H40: 1
A41: 贺泓 | B41: 中国科学院生态环境研究中心 | C41: 名冠金凯悦酒店 | D41: 豪华套房 | H41: 1
A42: 吴丰昌 | B42: 中国环境科学研究院 | C42: 名冠金凯悦酒店 | D42: 豪华套房 | H42: 1
A43: 朱永官 | B43: 中国科学院生态环境研究中心 | C43: 名冠金凯悦酒店 | D43: 豪华套房 | H43: 1
A44: 余刚 | B44: 北京师范大学 | C44: 名冠金凯悦酒店 | D44: 豪华套房 | H44: 1
A45: 徐义刚 | B45: 中国科学院广州地球化学研究所 | C45: 名冠金凯悦酒店 | D45: 豪华套房
A46: 何宏平 | B46: 中国科学院广州地球化学研究所 | C46: 名冠金凯悦酒店 | D46: 豪华套房
A47: 王焰新 | B47: 中国地质大学（武汉） | C47: 名冠金凯悦酒店 | D47: 豪华套房 | H47: 1
A48: 魏迪（院士） | B48: 中国科学院北京纳米能源与系统研究所 | C48: 名冠金凯悦酒店 | D48: 豪华套房 | H48: 1
A49: 任南琪 | B49: 哈尔滨工业大学 | C49: 名冠金凯悦酒店 | D49: 豪华亲子套房 | H49: 1
A50: 任洪强 | B50: 南京大学 | C50: 名冠金凯悦酒店 | D50: 豪华亲子套房 | H50: 1
A51: 侯立安 | B51: 中国人民解放军火箭军工程大学、火箭军后勤科学技术研究所 | C51: 名冠金凯悦酒店 | D51: 豪华亲子套房 | H51: 1
A52: 刘文清 | B52: 中国科学技术大学 | C52: 名冠金凯悦酒店 | D52: 豪华亲子套房 | H52: 1
A54: 蒋建东 | B54: 中国医学科学院药物研究所 | C54: 名冠金凯悦酒店 | D54: 豪华亲子套房 | H54: 1
A55: 陈春英 | B55: 国家纳米科学中心、中国科学院纳米生物效应与安全性重点实验室 | C55: 名冠金凯悦酒店 | D55: 行政套房 | H55: 1
A56: 高翔 | B56: 大连理工大学 | C56: 名冠金凯悦酒店
A57: 魏复盛 | B57: 中国环境监测总站、中国科学技术大学 | C57: 名冠金凯悦酒店 | D57: 豪华亲子套房 | H57: 1
A58: 黄建平 | B58: 兰州大学、西部生态安全省部共建协同创新中心、半干旱气候变化教育部重点实验室主任 | C58: 名冠金凯悦酒店 | D58: 豪华亲子套房 | H58: 1
A59: 叶国安（院士） | C59: 江门富力万达嘉华酒店 | D59: 豪华套房 | E59: 45989 | H59: 1 | I59: 920 | K59: 大会免住宿
A60: 赵进才 | B60: 中国科学院化学研究所 | C60: 江门富力万达嘉华酒店 | D60: 豪华套房 | E60: 28日到 | H60: 1 | I60: 920 | L60: 两张餐票，要最好的套房
A61: 唐波 | B61: 崂山国家实验室 | C61: 名冠金凯悦酒店 | D61: 豪华亲子套房 | E61: 45990 | F61: 45992 | G61: =F61-E61 -> 2 | H61: 1 | I61: 519 | J61: =I61*H61*G61 -> 1038 | K61: 大会免住宿 | L61: 专家个人已预订龙泉
A62: 唐波随行人员 | C62: 名冠金凯悦酒店 | D62: 商务单人房 | E62: 45990 | F62: 45992 | G62: 2 | H62: 1 | I62: 470 | J62: =I62*H62*G62 -> 940
A63: 陈荣 | B63: 西安建筑科技大学副校长 | C63: 江门富力万达嘉华酒店 | D63: 豪华大床房 | H63: 1
A64: 张杭君 | B64: 53分会，杭州师范大学副校长 | C64: 江门富力万达嘉华酒店 | D64: 豪华大床房 | E64: 45989 | F64: 45991 | G64: =F64-E64 -> 2 | H64: 1 | I64: 438 | J64: =G64*H64*I64 -> 876 | K64: 专家自付
A65: 桑楠 | B65: 山西能源学院党委副书记、院长 | C65: 江门富力万达嘉华酒店 | D65: 行政大床房 | E65: 45989 | F65: 45993 | G65: =F65-E65 -> 4 | H65: 0 | L65: 专家已自行线上预定
A66: 潘学军 | B66: 昆明理工大学副校长 | C66: 江门富力万达嘉华酒店 | D66: 豪华大床房 | H66: 1
A67: 蔡宗苇 | B67: 宁波东方理工大学协理副校长 | C67: 江门富力万达嘉华酒店 | D67: 豪华大床房 | H67: 1
A68: 茂 | B68: 暨南大学原校长 | C68: 江门富力万达嘉华酒店 | D68: 豪华大床房 | H68: 1
A69: 李和兴 | B69: 原校长 | C69: 江门富力万达嘉华酒店 | D69: 豪华大床房 | E69: 45990 | F69: 45991 | G69: =F69-E69 -> 1 | H69: 1 | I69: 438 | J69: =G69*H69*I69 -> 438
A70: 葛飞 | B70: 湘潭大学副校长 | C70: 江门富力万达嘉华酒店 | D70: 豪华大床房 | H70: 0 | L70: 范朝霞已代订江门华保体育会展酒店（广东珠西国际会展中心滨江体育中心店）
A71: 王沛芳 | B71: 华北水利水电大学 | C71: 名冠金凯悦酒店 | D71: 主题养生单人房 | H71: 1 | I71: 470 | K71: 专家自付
A72: 刘思金团队5人 | B72: 84分会 | C72: 江门富力万达嘉华酒店 | D72: 高级大床房 | H72: 5 | I72: 470 | K72: 专家自付
A73: 曹宏斌院士 | C73: 名冠金凯悦酒店 | D73: 豪华套房 | E73: 待定 | H73: 1 | I73: 519 | K73: 大会免住宿
A74: 李俊华院士 | B74: 17分会 清华大学 | C74: 名冠金凯悦酒店 | D74: 豪华套房 | E74: 待定 | H74: 1 | I74: 519
A76: Wonyong Choi（院士） | B76: 姜晓刚 ACS | C76: 江门富力万达嘉华酒店 | D76: 行政大床房 | E76: 45989 | F76: 45993 | G76: 4 | H76: 1 | I76: 470 | J76: 1880 | K76: 大会免住宿 | L76: 分会院士、刘长宇
A77: Trevor David Waite（院士） | B77: 姜晓刚 ACS | C77: 江门富力万达嘉华酒店 | D77: 行政大床房 | E77: 45989 | F77: 45993 | G77: 4 | H77: 1 | I77: 470 | J77: 1880 | K77: 大会免住宿 | L77: 刘长宇
A78: Michael Siu 萧锦荣 （院士） | C78: 江门富力万达嘉华酒店 | D78: 豪华套房 | E78: 45989 | F78: 45992 | G78: 3 | H78: 1 | I78: 920 | J78: =G78*H78*I78 -> 2760 | K78: 大会免住宿 | L78: 刘长宇
A79: 乐晓春（院士） | B79: Xing-Fang Li 同住 | C79: 江门富力万达嘉华酒店 | D79: 行政大床房 | E79: 45989 | F79: 45993 | G79: =F79-E79 -> 4 | H79: 1 | I79: 470 | J79: =G79*H79*I79 -> 1880 | K79: 大会免住宿 | L79: 刘长宇
A80: Derek Charles Gordon Muir（院士） | C80: 名冠金凯悦酒店 | D80: 行政单人房 | E80: 45989 | F80: 45993 | G80: 4 | H80: 1 | I80: 438 | J80: =G80*H80*I80 -> 1752 | K80: 大会免住宿 | L80: 分会院士、刘长宇
A81: Paul Westerhoff（院士） | C81: 江门富力万达嘉华酒店 | D81: 行政大床房 | E81: 45990 | F81: 45994 | G81: 4 | H81: 1 | I81: 470 | J81: =G81*H81*I81 -> 1880 | K81: 大会免住宿 | L81: 刘长宇29
A82: Pedro J.J. Alvarez（院士） | C82: 江门富力万达嘉华酒店 | D82: 行政大床房 | E82: 45990 | F82: 45994 | G82: 4 | H82: 1 | I82: 470 | J82: =G82*H82*I82 -> 1880 | K82: 大会免住宿 | L82: 刘长宇29
A83: Madelyn Whitaker（Pedro助手） | C83: 江门富力万达嘉华酒店 | D83: 高级大床房 | E83: 45990 | F83: 45994 | G83: 4 | H83: 1 | I83: 470 | J83: =G83*H83*I83 -> 1880 | K83: 大会免住宿 | L83: 刘长宇29
A84: Zhiguo Yuan（院士） | C84: 江门富力万达嘉华酒店 | D84: 行政大床房 | E84: 45989 | F84: 45993 | G84: 3 | H84: 1 | I84: 470 | J84: =G84*H84*I84 -> 1410 | K84: 大会免住宿 | L84: 刘长宇29
A85: Abror Gadaev | C85: 名冠金凯悦酒店 | D85: 豪华套房 | E85: 45990 | F85: 45993 | G85: 3 | H85: 1 | I85: 470 | J85: =G85*H85*I85 -> 1410 | K85: 大会免住宿
A86: Lee Hian Kee | C86: 江门富力万达嘉华酒店 | D86: 行政大床房 | E86: 45989 | F86: 45991 | G86: =F86-E86 -> 2 | H86: 1 | I86: 470 | J86: =I86*G86*H86 -> 940 | K86: 大会免住宿 | L86: 刘长宇
A87: 唐盛 | B87: Lee Hian Kee同行 | C87: 江门富力万达嘉华酒店 | D87: 高级大床房 | E87: 45989 | F87: 45991 | G87: =F87-E87 -> 2 | H87: 1 | I87: 470 | J87: =I87*G87*H87 -> 940
A88: 郑焰 | B88: 南方科技大学 | C88: 江门保利皇冠假日酒店（园山湖店） | D88: 高级城景大床房 | E88: 45989 | F88: 45990 | G88: 1 | H88: 0 | I88: 550 | J88: 500 | K88: 大会免住宿，预订平台已登记1间
C89: 江门富力万达嘉华酒店 | D89: 行政大床房 | E89: 45990 | F89: 45993 | G89: 2 | H89: 1 | I89: 470 | J89: =G89*I89*H89 -> 940 | K89: 大会免住宿
A90: 赵美训 | C90: 江门富力万达嘉华酒店 | D90: 豪华大床房 | E90: 45989 | F90: 45990 | G90: 1 | H90: 0 | I90: 470 | J90: =G90*I90*H90 -> 0 | K90: 大会免住宿，预订平台已登记1间
A91: 张山青 | B91: 广东工业大学 | C91: 江门富力万达嘉华酒店 | D91: 豪华大床房 | E91: 45989 | F91: 45993 | G91: 4 | H91: 0 | I91: 470 | J91: 1880 | K91: 免住宿，预订平台已登记1间
A92: Li Qilin 李琪琳 | B92: 29分会 | C92: 江门富力万达嘉华酒店 | D92: 高级大床房 | E92: 45990 | F92: 45994 | G92: 4 | H92: 1 | I92: 470 | J92: 1880 | K92: 大会免住宿 | L92: 刘长宇29
A93: Yongsheng Chen 陈勇生 | C93: 江门富力万达嘉华酒店 | D93: 高级大床房 | E93: 45990 | F93: 45994 | G93: 4 | H93: 1 | I93: 470 | J93: 1880 | K93: 大会免住宿 | L93: 刘长宇29
A94: Zhiyong Ren 任智勇 | C94: 江门富力万达嘉华酒店 | D94: 高级大床房 | E94: 45990 | F94: 45993 | G94: 3 | H94: 1 | I94: 470 | J94: =G94*H94*I94 -> 1410 | K94: 大会免住宿 | L94: 刘长宇29
A95: 阮挺 | B95: 六个闭幕式综述报告人 | C95: 江门富力万达嘉华酒店 | D95: 行政双床房 | E95: 45989 | F95: 45993 | G95: 4 | H95: 1 | I95: 470 | J95: 1880
A96: 张新星 | C96: 江门富力万达嘉华酒店 | D96: 行政大床房 | E96: 45989 | F96: 45993 | G96: 4 | H96: 1 | I96: 470 | J96: 1880 | K96: 大会免住宿
A97: 邢明阳 | C97: 江门富力万达嘉华酒店 | D97: 行政大床房 | H97: 1
A98: 王书肖 | C98: 江门保利皇冠假日酒店（园山湖店） | D98: 高级湖景大床房 | E98: 45989 | F98: 45993 | G98: =F98-E98 -> 4 | H98: 1 | I98: 550 | J98: =G98*I98*H98 -> 2200 | K98: 大会免住宿
A99: 宋扬 | C99: 江门富力万达嘉华酒店 | D99: 行政大床房 | E99: 45989 | F99: 45993 | G99: 4 | H99: 1 | I99: 470 | J99: 1880 | K99: 大会免住宿
A100: 史薇 | C100: 江门富力万达嘉华酒店 | D100: 行政大床房 | E100: 45989 | F100: 45993 | G100: 4 | H100: 1 | I100: 470 | J100: 1880 | K100: 大会免住宿
A101: 朱相宇 | B101: 99分会，海外青年22人 | C101: 新会碧桂园凤悦凤凰酒店 | D101: 高级大床房(单早) | E101: 45989 | F101: 45993 | G101: 4 | H101: 1 | I101: 280 | J101: =G101*H101*I101 -> 1120 | K101: 大会免住宿 | L101: 22名 海外学者
A102: 吴盛华 | D102: 高级大床房(单早) | E102: 45989 | F102: 45994 | G102: 5 | H102: 1 | I102: 280 | J102: =G102*H102*I102 -> 1400
A103: 曾金金 | D103: 高级大床房(单早) | E103: 45989 | F103: 45993 | G103: 4 | H103: 1 | I103: 280 | J103: =G103*H103*I103 -> 1120
A104: 张荆晶 | D104: 高级大床房(单早) | E104: 45989 | F104: 45993 | G104: 4 | H104: 1 | I104: 280 | J104: =G104*H104*I104 -> 1120
...

Sheet 外籍专家预留
A1: 第十三届全国环境化学大会外籍专家用房登记（收集结果）
A3: 序号 | B3: 提交者 | C3: 联系人 | D3: 联系方式 | E3: 证件名称 | F3: 证件号码 | G3: 入住酒店 | H3: 房型 | I3: 入住日期 | J3: 退房日期 | K3: 入住天数 | L3: 房间数量（间） | M3: 酒店单价（元） | N3: 应收房费（元） | O3: 备注 | P3: 收费形式
A4: 1 | B4: 刘素琴 | C4: 刘素琴 | D4: 13466371647 | E4: HG627404 | F4: X. Chris Le | G4: 江门富力万达嘉华酒店 | H4: 豪华大床房 | I4: 45989 | J4: 45993 | K4: 4 | L4: 1 | M4: 470 | N4: 1880 | O4: Xing-Fang Li 同住 | P4: POS机支付
A5: 2 | B5: Xiangru 张相如 | C5: 张相如 | D5: 14714315819 | E5: 张相如 | F5: H60155102 | G5: 江门富力万达嘉华酒店 | H5: 豪华大床房 | I5: 45989 | J5: 45993 | K5: 4 | L5: 1 | M5: 470 | N5: 1880 | P5: POS机支付
A6: 3 | B6: RN | C6: Raman Novikau | D6: 17868746908 | E6: Passport | F6: AB3489892 | G6: 江门银晶国际酒店 | H6: 大床房 | I6: 45988 | J6: 45994 | K6: 6 | L6: 1 | M6: 200 | N6: 1200 | P6: 微信/支付宝扫码支付
A7: 4 | B7: Qihong Lu | C7: 鲁祺鸿 | D7: 13430392474 | E7: He jianzhong | F7: K2071792E | G7: 江门富力万达嘉华酒店 | H7: 豪华双床房（无房，改行政双床） | I7: 45989 | J7: 45992 | K7: 3 | L7: 1 | M7: 470 | N7: 1410 | O7: 带小朋友最好有儿童房 | P7: 微信/支付宝扫码支付
A8: 5 | B8: 周蕾 | C8: 周蕾 | D8: 15010132107 | E8: Lucia Muñoz Franco | F8: NP9H53J18 | G8: 江门富力万达嘉华酒店 | H8: 豪华大床房 | I8: 45989 | J8: 45993 | K8: 4 | L8: 2 | M8: 470 | N8: 3760 | P8: POS机支付
A9: 6 | B9: 孔多多 | C9: 于志刚 | D9: 18569509240 | E9: 于志刚 | F9: EQ6317073 | G9: 名冠金凯悦酒店 | H9: 豪华大床房 | I9: 45989 | J9: 45994 | K9: 5 | L9: 1 | M9: 438 | N9: 2190 | P9: POS机支付
A10: 7 | B10: Paul | C10: 王坡 | D10: 18565359691 | E10: Charles Shiu Wong | F10: 56662970 | G10: 名冠金凯悦酒店 | H10: 豪华大床房 | I10: 45989 | J10: 45993 | K10: 4 | L10: 1 | M10: 438 | N10: 1752
A11: 8 | B11: 孔多多 | C11: 孔德懿 | D11: 17768103485 | E11: Jianhua Guo | F11: EB4922180 | G11: 名冠金凯悦酒店 | H11: 豪华大床房 | I11: 45989 | J11: 45993 | K11: 4 | L11: 1 | M11: 438 | N11: 1752 | O11: 召集人 | P11: POS机支付
A12: 9 | B12: 西小瓜 | C12: 杨晓溪 | D12: 18810982539 | E12: JEONGEUN OH | F12: M95504585 | G12: 江门富力万达嘉华酒店 | H12: 豪华大床房 | I12: 45989 | J12: 45992 | K12: 3 | L12: 1 | M12: 470 | N12: 1410 | O12: 联系人支付房费 | P12: 微信/支付宝扫码支付
A13: 10 | B13: 想五天 | C13: 伍天翔 | D13: 18342207307 | E13: Daniel Keith Schlenk | F13: A03580668 | G13: 名冠金凯悦酒店 | H13: 臻享商务单人房（75寸彩电）（单早） | I13: 45989 | J13: 45994 | K13: 5 | L13: 1 | M13: 470 | N13: 2350
A14: 11 | B14: 姜晓刚 ACS | C14: 姜晓刚 | D14: 13051706665 | E14: Margaret Mills | F14: 547817624 | G14: 江门富力万达嘉华酒店 | H14: 豪华双床房（无房，改行政双床） | I14: 45989 | J14: 45993 | K14: 4 | L14: 1 | M14: 470 | N14: 1880 | P14: POS机支付
A15: 12 | B15: Qihong Lu | C15: 鲁祺鸿 | D15: 13430392474 | E15: Bayeshova Saltant | F15: N16193992 | G15: 江门富力万达嘉华酒店 | H15: 豪华双床房（无房，改行政双床） | I15: 45989 | J15: 45992 | K15: 3 | L15: 1 | M15: 470 | N15: 1410 | O15: 与Nurzhanova Assil 同住 | P15: 微信/支付宝扫码自付
A16: 13 | B16: LB | C16: 梁斌 | D16: 13910740863 | E16: Hnkolaeb/Nikolave | F16: 758939538 | G16: 江门富力万达嘉华酒店 | H16: 豪华双床房（无房，改行政双床） | I16: 45989 | J16: 45992 | K16: 3 | L16: 2 | M16: 470 | N16: 2820 | O16: 大床+双床各一个，填的房间数3间，按高级大床1间+豪华双床2间 | P16: POS机支付
H17: 高级大床房 | I17: 45989 | J17: 45992 | K17: 3 | L17: 1 | M17: 470 | N17: 1410
A18: 14 | B18: Paul | C18: 王坡 | D18: 18565359691 | E18: Derek Charles Gordon Muir | F18: HM321274 | G18: 名冠金凯悦酒店 | H18: 豪华大床房 | I18: 45989 | J18: 45993 | K18: 4 | L18: 1 | M18: 438 | N18: 1752 | O18: 加拿大皇家科学院院士免住宿费（五邑大学初步计划由组委会付房费） | P18: 微信/支付宝扫码自付
A19: 15 | B19: 李萌 | C19: 李萌 | D19: 18810153826 | E19: Grace Evelyn Thoburn | F19: 131183487 | G19: 名冠金凯悦酒店 | H19: 豪华大床房 | I19: 45988 | J19: 45994 | K19: 6 | L19: 1 | M19: 438 | N19: 2628 | P19: 微信/支付宝扫码自付
A20: 16 | B20: 姜晓刚 ACS | C20: 姜晓刚 | D20: 13051706665 | E20: Wonyong Choi | F20: M477K8635 | G20: 江门富力万达嘉华酒店 | H20: 豪华大床房 | I20: 45989 | J20: 45993 | K20: 4 | L20: 1 | M20: 470 | N20: 1880 | O20: 美国外籍院士 | P20: POS机支付
A21: 17 | B21: 李萌 | C21: 李萌 | D21: 18810153826 | E21: Peter Vikesland | F21: A80684012 | G21: 名冠金凯悦酒店 | H21: 豪华大床房 | I21: 45991 | J21: 45994 | K21: 3 | L21: 1 | M21: 438 | N21: 1314
C22: 萧锦荣 | D22: 13853128391 | E22: SIU, KAM WING MICHAEL | F22: H04254584 | G22: 江门富力万达嘉华酒店 | H22: 豪华大床房 | I22: 45989 | J22: 45992 | K22: 3 | L22: 1 | M22: 470 | N22: 1410 | P22: 微信/支付宝扫码自付
C23: 姜晓刚 | D23: 13051706665 | E23: Trevor David Waite | F23: RA2015710 | G23: 江门富力万达嘉华酒店 | H23: 豪华大床房 | I23: 45989 | J23: 45993 | K23: 4 | L23: 1 | M23: 470 | N23: 1880 | O23: 美国外籍院士，大会付费（备注大会付费，由组委会付房费？） | P23: POS机支付
C24: 孔德懿 | D24: 17768103485 | E24: Mengyan Li | F24: EK0010988 | G24: 江门名冠金凯悦酒店 | H24: 豪华大床房 | I24: 45989 | J24: 45993 | K24: 4 | L24: 1 | M24: 438 | N24: 1752 | P24: POS机支付

Sheet 特殊事项备注
A1: 订单号/注册号 | B1: 姓名 | C1: 电话 | D1: 预订酒店 | E1: 房型 | F1: 入住时间 | G1: 备注 | H1: 备注
A2: 20695273 | B2: 邹依霖 | C2: 13039330050 | D2: 江门丽宫国际酒店 | E2: A座高级双床房 | G2: 需要再加一张床
A3: 4138 | B3: 侯德义 | C3: 18548911918 | D3: 江门富力万达嘉华酒店（VIP预留） | E3: 豪华大床房 | G3: 需要酒店开票
A4: 778 | B4: 申芳霞 | C4: 15210592958 | D4: 江门富力万达嘉华酒店 | E4: 豪华大床房(单 | G4: 将入住时间从“11.27-12.1日”改为“11.28-12.2日” | H4: 已修改
A5: 4734 | B5: 乔琰 | C5: 15210592958 | D5: 江海智选假日酒店 | E5: 大床房 | G5: 将入住时间从“11.28-12.2日”改为“11.28-12.1日” | H5: 重复
A6: 2616 | B6: 陈洁 | C6: 15373575957 | D6: 间维也纳酒店(江门常安路步行街店) | E6: 豪华双床房 | G6: 将入住时间从“11.28-12.1日”改为“11.28-12.2日” | H6: 重复
B7: 周婧 | C7: 18099242227 | D7: 江门新会碧桂园凤悦凤凰酒店 | E7: 2间大床+1间双床 | F7: 11.28日-12-2日 | G7: 预留，自行线下支付
B8: 谢静 | C8: 北京理工大学 | D8: 江门蓬江华茵广场亚朵酒店 | G8: 将入住时间从“11.28-12.2日”改为“11.28-12.1日” | H8: 重复
B9: 王丁一 | C9: 中科院生态环境研究中心 | D9: 江门富力万达嘉华酒店 | E9: 豪华双床房 | F9: 11.28日-12-2日 | G9: 将入住时间从“11.28-12.2日”改为“11.28-12.1日” | H9: 重复
A10: 4152 | B10: 郑明辉 | C10: 13621093063 | D10: 江门富力万达嘉华酒店（VIP预留） | E10: 行政大床房（单早）/整间/CNY470.00/天 | G10: 万达套房，11.28—2日
B11: 姜璐 | D11: 江门富力万达嘉华酒店（VIP预留） | E11: 高级双床房（双早）（整间） | F11: 2025-11-27 2025-12-02 | G11: 跟陈伟芳合住，金额对半，发票分开开，一半为内蒙古大学的发票信息（纳税人识别号：1215000046002920XK）具体见下方，一半为中国科学院生态环境研究中心（纳税人识别号：121000004000122540） 名称：内蒙古大学 纳税人识别号：1215000046002920XK 单位地址：呼和浩特市赛罕区大学西路235号 电话号码：0471-4994142 开户行：中国建设银行股份有限公司呼和浩特赛罕区支行 联行号：105191075085 银行账号：15001706667050001905
B12: 张建清 | G12: 尊敬的会务组老师， 你好！因单位财务报账要求，我科室2名参会人员需提前开具注册费和酒店住宿费发票，申请人信息如下： 单位：深圳市疾病预防控制中心，申请人1姓名：张建清，手机号：13501580586，邮箱：969676617@qq.com； 申请人2：彭金铃，13688815730，邮箱：453448942@qq.com。谢谢！ | H12: 已修改
G13: 我预定了环化大会期间维也纳酒店(江门常安路步行街店) 豪华双床房（双早） 2间3晚（11月28日入住-12月1日离店）。现因行程变动，2间房均需延长一晚至12月2日离店，请帮忙处理，谢谢！ 联系方式：陈女士（电话：15373575957） | H13: 已处理
G14: 您好，我预定了江门丽宫国际酒店（VIP预留） A座高级大床房（单早） （整间） （2*6晚） 我在网站上申请了退款，但担心退款成功后没有房间了，所以发邮件问一下是否能帮忙直接修改，保留我的订单，将入住日期修改成11月28日，退房日期为12月2日，房间数量修改为1间。谢谢！ 史亚利 中国科学院生态环境研究中心 环境化学与生态毒理学国家重点实验室 离子色谱和新型污染物分析研究组 e-mail:shiyali@rcees.ac.cn | H14: 已处理
G15: 您好，我的订单房间日期选错了，应为11.28入住，12.2日退房。麻烦帮忙进行变更 订单信息见附件。 谢谢。 祝好 芳霞 =============================== 申芳霞 博士 卓越百人副教授 能源与动力工程学院 北京航空航天大学 Mobile: (+86) 15210592958 Email: fxshen@buaa.edu.cn | H15: 已处理
G16: =_xlfn.DISPIMG("ID_06507F065DEA4E858E4DC8F8E87C7C63",1) -> =DISPIMG("ID_06507F065DEA4E858E4DC8F8E87C7C63",1) | H16: 具体信息：杨超 豪华大床房 我原预定的酒店江门富力万达嘉华酒店11月28至12月1日 3晚，请更改至11月29日至11月30日 1晚。 | I16: 不改了，已处理
G17: 大会组委会，您好！ 我是中国科学院生态环境研究中心刘稷燕，为参加环化大会，我已经预定住宿并已经缴纳了费用（1500元），缴费记录请见附件。依据目前安排好的行程，我的住宿希望变更为11月28日入住，12月2日离店，住宿4晚，麻烦您帮忙作住宿时间变更，谢谢！ 刘稷燕 | H17: 已修改等付费
G18: 会务组您好： 麻烦将我预定的丽宫酒店20251128-20251202的酒店改成11月30号到-12月2号离店两个晚上的大床房（单早）。 谢谢 祝好 罗一丹 20251110 | H18: 已更改
G19: 您好： 我是郑光洁（个人代表信息 注册号：3922）， 我预定了12.27-12.2的“江门富力万达嘉华酒店（VIP预留）“，订单编号21198109，订单信息如附件。 现因行程变更，希望将预订信息更改为： 12.28（入住）-12.30（退房），共2晚 房型及其它信息不变。 请协助变更。谢谢！ 祝好， 郑光洁 | H19: 已更改
G20: 会务组老师好，我是西北农林科技大学的贾汉忠，电话15399421323，会议注册号3895。之前预定了 名冠金凯悦酒店（VIP预留酒店）且付费，原计划入住时间11月28日，现需要变更为29日入住，请给予处理。 发自我的手机 | H20: 不听电话
G21: 您好，我预定了江门丽宫国际酒店（VIP预留） A座高级大床房（单早） （整间） （2*6晚） 我在网站上申请了退款，但担心退款成功后没有房间了，所以发邮件问一下是否能帮忙直接修改，保留我的订单，将入住日期修改成11月28日，退房日期为12月2日，房间数量修改为1间。谢谢！ 史亚利 中国科学院生态环境研究中心 环境化学与生态毒理学国家重点实验室 离子色谱和新型污染物分析研究组 e-mail:shiyali@rcees.ac.cn | H21: 已处理
G22: 会务组老师好，我是西北农林科技大学的贾汉忠，电话15399421323，会议注册号3895。之前预定了 名冠金凯悦酒店（VIP预留酒店）且付费，原计划入住时间11月28日，现需要变更为29日入住，请给予处理。 发自我的手机 | H22: 不听电话
G23: 尊敬的环化大会工作人员： 您好！ 我是冯翠杰，我已预定了江门丽宫国际酒店，11月28日至12月2日的酒店（4个晚上），订单信息如下截图。但是由于行程有变，麻烦您将酒店入住时间修改为11月28日至12月2日，共2个晚上。 请问如何操作，我已支付过费用，如何退掉多支付的部分？ 谢谢，盼复。 预祝会议取得圆满成功。 | H23: 已修改
G24: 您好， 我之前在网上预订了铂顿国际公寓江门蓬江行政服务中心店11.28入住 12.1退房 （详见截图） 现行程有变，11.28入住，11.30日退房。还请您帮助修改。 非常感谢！ 宋文静 | H24: 不听电话
G25: 会务老师， 您好！山东大学薛丽坤老师（个人代表，注册号2653）参加第十三届环境化学大会，已经预定了酒店房间并支付费用（名冠金凯悦酒店（VIP预留），广东省江门蓬江区发展大道188号），原定11月29日入住，12月1日退房，共2个晚上，费用876元已支付，详细信息见附件。由于工作安排有变动，需要改为11月29日入住（入住时间不变），11月30日退房（提前一天退房），特申请变更住宿日期，并烦请原路退回一晚住宿费用。给您带来不便之处敬请谅解！如有问题请联系我，电话18266208096，谢谢！ 祝好！ 连曦 山东大学环境研究院 0532-58631962，18266208096 lianxi@sdu.edu.cn | H25: 已修改
B26: 刘倩 | C26: 18810276437 | F26: 将退房时间延长至12月1日，订单编号（21090324） | G26: =_xlfn.DISPIMG("ID_1D1D1CFD776343ACAA1454DE8116F2F3",1) -> =DISPIMG("ID_1D1D1CFD776343ACAA1454DE8116F2F3",1) | H26: 已处理
B27: 杨欣 | D27: 江门丽宫国际酒店 | F27: 将入住时间从“11.28-12.1日”改为“11.28-11.30日” | G27: =_xlfn.DISPIMG("ID_8318A49599604442A361CFF80441F9A9",1) -> =DISPIMG("ID_8318A49599604442A361CFF80441F9A9",1)
B28: 侯杰 | D28: 名冠金凯悦酒店 | F28: 林道辉教授想把原订酒店的日期调整到11.28入住-12.1离店。 侯杰想调整到11.28入住-11.30离店. | G28: =_xlfn.DISPIMG("ID_D27DDDC814D54421A08C71255BB15535",1) -> =DISPIMG("ID_D27DDDC814D54421A08C71255BB15535",1)
G29: 申请人信息 姓名:汪金辉; 手机号:15365346625; 注册号:6343。 发票抬头:上海交通大学 税号: 1210000042500615X0 备注：汪金辉住宿，11.28-12.02 | H29: 要开发票
G30: 注册人姓名：丁玎， 单位：北京市科学技术研究院城市安全与环境科学研究所 注册人手机号：18810810622 注册号：1999 | H30: 要开发票

Sheet WpsReserved_CellImgList
